<?xml version="1.0" encoding="utf-8"?>
<Level Mode="1" Step="7">
  <Hexagons>
    <Hexagon X="1" Y="1" BlockState="0" UpperState="1" LowerState="0" />
    <Hexagon X="4" Y="1" BlockState="0" UpperState="1" LowerState="0" />
  </Hexagons>
  <Pieces>
    <Piece X="0" Y="0" Upper="1" State="0" Type="0" />
    <Piece X="1" Y="0" Upper="1" State="0" Type="0" />
    <Piece X="3" Y="0" Upper="1" State="0" Type="0" />
    <Piece X="5" Y="0" Upper="1" State="0" Type="0" />
    <Piece X="6" Y="0" Upper="1" State="0" Type="0" />
    <Piece X="2" Y="2" Upper="0" State="0" Type="0" />
    <Piece X="0" Y="5" Upper="0" State="0" Type="0" />
    <Piece X="1" Y="5" Upper="0" State="0" Type="0" />
  </Pieces>
  <Walls />
  <Groups />
  <Switchers />
  <Clocks />
  <Twines />
  <Ices />
  <Steps>
    <Step Index="5" Direction="3" />
    <Step Index="2" Direction="1" />
    <Step Index="2" Direction="5" />
    <Step Index="7" Direction="4" />
    <Step Index="6" Direction="4" />
    <Step Index="7" Direction="3" />
    <Step Index="2" Direction="5" />
  </Steps>
</Level>